odoo/addons/l10n_ec_withhold/README.rst
odoo/addons/l10n_ec_withhold/__init__.py
odoo/addons/l10n_ec_withhold/__manifest__.py
odoo/addons/l10n_ec_withhold/data/edi_withhold.xml
odoo/addons/l10n_ec_withhold/data/template/account.journal-ec.csv
odoo/addons/l10n_ec_withhold/i18n/l10n_ec_withhold.pot
odoo/addons/l10n_ec_withhold/models/__init__.py
odoo/addons/l10n_ec_withhold/models/account_chart_template.py
odoo/addons/l10n_ec_withhold/models/account_edi_document.py
odoo/addons/l10n_ec_withhold/models/account_edi_format.py
odoo/addons/l10n_ec_withhold/models/account_fiscal_position.py
odoo/addons/l10n_ec_withhold/models/account_journal.py
odoo/addons/l10n_ec_withhold/models/account_move.py
odoo/addons/l10n_ec_withhold/models/data.py
odoo/addons/l10n_ec_withhold/models/res_partner.py
odoo/addons/l10n_ec_withhold/readme/CONTRIBUTORS.md
odoo/addons/l10n_ec_withhold/readme/DESCRIPTION.md
odoo/addons/l10n_ec_withhold/readme/USAGE.md
odoo/addons/l10n_ec_withhold/report/__init__.py
odoo/addons/l10n_ec_withhold/report/report_edi_withhold.xml
odoo/addons/l10n_ec_withhold/report/report_invoice.xml
odoo/addons/l10n_ec_withhold/security/ir.model.access.csv
odoo/addons/l10n_ec_withhold/static/description/icon.png
odoo/addons/l10n_ec_withhold/static/description/index.html
odoo/addons/l10n_ec_withhold/tests/__init__.py
odoo/addons/l10n_ec_withhold/tests/test_account_journal.py
odoo/addons/l10n_ec_withhold/tests/test_common.py
odoo/addons/l10n_ec_withhold/tests/test_l10n_ec_purchase_withhold.py
odoo/addons/l10n_ec_withhold/tests/test_l10n_ec_sale_withhold.py
odoo/addons/l10n_ec_withhold/views/account_fiscal_position_view.xml
odoo/addons/l10n_ec_withhold/views/account_journal_view.xml
odoo/addons/l10n_ec_withhold/views/account_move_view.xml
odoo/addons/l10n_ec_withhold/views/menu_root.xml
odoo/addons/l10n_ec_withhold/views/res_partner_view.xml
odoo/addons/l10n_ec_withhold/wizard/__init__.py
odoo/addons/l10n_ec_withhold/wizard/account_move_send.py
odoo_addon_l10n_ec_withhold-17.0.1.0.1.dist-info/METADATA
odoo_addon_l10n_ec_withhold-17.0.1.0.1.dist-info/WHEEL
odoo_addon_l10n_ec_withhold-17.0.1.0.1.dist-info/top_level.txt
odoo_addon_l10n_ec_withhold-17.0.1.0.1.dist-info/RECORD
